linecover/__init__.py
linecover/checker.py
linecover/cli.py
linecover/display.py
linecover/models.py
linecover/parser.py
linecover/reporter.py
linecover/runner.py
linecover/violations.py
linecover_hook-0.1.0.dist-info/METADATA
linecover_hook-0.1.0.dist-info/WHEEL
linecover_hook-0.1.0.dist-info/entry_points.txt
linecover_hook-0.1.0.dist-info/licenses/LICENSE
linecover_hook-0.1.0.dist-info/RECORD
