Metadata-Version: 2.4
Name: linecover-hook
Version: 0.1.0
Summary: Code coverage enforcement tool with flake8-style reporting
License-Expression: BSD-3-Clause
License-File: LICENSE
Requires-Python: >=3.12
Requires-Dist: click>=8.1.7
Requires-Dist: coverage>=7.13.0
Requires-Dist: loguru>=0.7.3
Provides-Extra: dev
Requires-Dist: pytest-cov>=6.0.0; extra == 'dev'
Requires-Dist: pytest>=9.0.2; extra == 'dev'
